{
  "ICP": {
    "current_run": 26,
    "status": "post_exit",
    "entry_time": "2026-02-09T08:31:25.669625",
    "exit_time": "2026-02-09T10:37:20.816192",
    "last_bar_collected": 4334,
    "tracking_until": "2026-02-19T10:37:20.816192",
    "entry_volume": 1084577.1900199999
  },
  "APT": {
    "current_run": 43,
    "status": "post_exit",
    "entry_time": "2026-02-18T20:26:47.301323",
    "exit_time": "2026-02-18T21:03:42.877681",
    "last_bar_collected": 4317,
    "tracking_until": "2026-02-28T21:03:42.877681",
    "entry_volume": 1674011.6660810004
  },
  "TIA": {
    "current_run": 34,
    "status": "post_exit",
    "entry_time": "2026-02-18T05:49:34.123674",
    "exit_time": "2026-02-18T06:44:44.258794",
    "last_bar_collected": 4251,
    "tracking_until": "2026-02-28T06:44:44.258794",
    "entry_volume": 1177522.4092989997
  },
  "NEAR": {
    "current_run": 40,
    "status": "post_exit",
    "entry_time": "2026-02-18T17:18:24.579763",
    "exit_time": "2026-02-18T19:09:22.045273",
    "last_bar_collected": 4248,
    "tracking_until": "2026-02-28T19:09:22.045273",
    "entry_volume": 1406598.9537899995
  },
  "PENGU": {
    "current_run": 41,
    "status": "post_exit",
    "entry_time": "2026-02-18T07:39:41.268635",
    "exit_time": "2026-02-18T10:03:23.803575",
    "last_bar_collected": 4301,
    "tracking_until": "2026-02-28T10:03:23.803575",
    "entry_volume": 1321379.0485200004
  },
  "WIF": {
    "current_run": 48,
    "status": "post_exit",
    "entry_time": "2026-02-16T22:26:43.490523",
    "exit_time": "2026-02-16T22:56:07.537251",
    "last_bar_collected": 4252,
    "tracking_until": "2026-02-26T22:56:07.537251",
    "entry_volume": 1351417.7424700004
  },
  "kBONK": {
    "current_run": 22,
    "status": "post_exit",
    "entry_time": "2026-02-14T17:33:20.475633",
    "exit_time": "2026-02-14T23:26:57.861420",
    "last_bar_collected": 4301,
    "tracking_until": "2026-02-24T23:26:57.861420",
    "entry_volume": 1283649.5327369992
  },
  "CRV": {
    "current_run": 37,
    "status": "post_exit",
    "entry_time": "2026-02-16T05:52:55.629613",
    "exit_time": "2026-02-16T08:27:32.582583",
    "last_bar_collected": 4280,
    "tracking_until": "2026-02-26T08:27:32.582583",
    "entry_volume": 3204835.2151949992
  },
  "AVNT": {
    "current_run": 38,
    "status": "post_exit",
    "entry_time": "2026-02-12T09:49:28.255954",
    "exit_time": "2026-02-12T11:24:42.562929",
    "last_bar_collected": 4266,
    "tracking_until": "2026-02-22T11:24:42.562929",
    "entry_volume": 1223879.458510001
  },
  "TAO": {
    "current_run": 43,
    "status": "post_exit",
    "entry_time": "2026-02-19T03:34:53.440080",
    "exit_time": "2026-02-19T07:15:59.218684",
    "last_bar_collected": 4249,
    "tracking_until": "2026-03-01T07:15:59.218684",
    "entry_volume": 5421573.215980002
  },
  "SPX": {
    "current_run": 72,
    "status": "in_top6",
    "entry_time": "2026-02-19T06:13:57.341157",
    "exit_time": null,
    "last_bar_collected": 4212,
    "tracking_until": null,
    "entry_volume": 5288406.681135
  },
  "VIRTUAL": {
    "current_run": 47,
    "status": "in_top6",
    "entry_time": "2026-02-19T07:58:45.918559",
    "exit_time": null,
    "last_bar_collected": 4307,
    "tracking_until": null,
    "entry_volume": 4747132.096569997
  },
  "TON": {
    "current_run": 48,
    "status": "post_exit",
    "entry_time": "2026-02-15T18:17:05.302512",
    "exit_time": "2026-02-15T20:16:42.880572",
    "last_bar_collected": 4269,
    "tracking_until": "2026-02-25T20:16:42.880572",
    "entry_volume": 1092279.5352399999
  },
  "PENDLE": {
    "current_run": 45,
    "status": "post_exit",
    "entry_time": "2026-02-15T23:16:14.627359",
    "exit_time": "2026-02-16T02:34:27.736131",
    "last_bar_collected": 4307,
    "tracking_until": "2026-02-26T02:34:27.736131",
    "entry_volume": 1318145.7779000003
  },
  "STABLE": {
    "current_run": 44,
    "status": "in_top6",
    "entry_time": "2026-02-19T08:46:10.854526",
    "exit_time": null,
    "last_bar_collected": 4320,
    "tracking_until": null,
    "entry_volume": 2355771.7318849997
  },
  "SEI": {
    "current_run": 21,
    "status": "post_exit",
    "entry_time": "2026-02-13T08:07:52.098329",
    "exit_time": "2026-02-13T11:07:45.005117",
    "last_bar_collected": 4308,
    "tracking_until": "2026-02-23T11:07:45.005117",
    "entry_volume": 2450497.329203
  },
  "KAITO": {
    "current_run": 29,
    "status": "post_exit",
    "entry_time": "2026-02-11T21:21:32.384074",
    "exit_time": "2026-02-12T05:09:14.241723",
    "last_bar_collected": 4332,
    "tracking_until": "2026-02-22T05:09:14.241723",
    "entry_volume": 1114914.7664400004
  },
  "IP": {
    "current_run": 48,
    "status": "post_exit",
    "entry_time": "2026-02-16T11:06:51.110706",
    "exit_time": "2026-02-16T17:22:59.395320",
    "last_bar_collected": 4199,
    "tracking_until": "2026-02-26T17:22:59.395320",
    "entry_volume": 1702593.4221500005
  },
  "CC": {
    "current_run": 72,
    "status": "post_exit",
    "entry_time": "2026-02-18T21:46:35.173196",
    "exit_time": "2026-02-18T23:49:25.588711",
    "last_bar_collected": 4256,
    "tracking_until": "2026-02-28T23:49:25.588711",
    "entry_volume": 1179285.3211200004
  },
  "WLFI": {
    "current_run": 43,
    "status": "post_exit",
    "entry_time": "2026-02-12T14:17:06.808319",
    "exit_time": "2026-02-12T18:08:24.097917",
    "last_bar_collected": 4316,
    "tracking_until": "2026-02-22T18:08:24.097917",
    "entry_volume": 3606818.1163830007
  },
  "ARB": {
    "current_run": 31,
    "status": "post_exit",
    "entry_time": "2026-02-13T22:55:11.091554",
    "exit_time": "2026-02-13T23:49:05.633809",
    "last_bar_collected": 4322,
    "tracking_until": "2026-02-23T23:49:05.633809",
    "entry_volume": 5105363.222409002
  },
  "JUP": {
    "current_run": 44,
    "status": "post_exit",
    "entry_time": "2026-02-19T05:11:45.077072",
    "exit_time": "2026-02-19T06:13:57.341157",
    "last_bar_collected": 4263,
    "tracking_until": "2026-03-01T06:13:57.341157",
    "entry_volume": 1536431.9498199995
  },
  "TRX": {
    "current_run": 61,
    "status": "post_exit",
    "entry_time": "2026-02-17T23:46:41.452170",
    "exit_time": "2026-02-18T04:48:23.603972",
    "last_bar_collected": 4260,
    "tracking_until": "2026-02-28T04:48:23.603972",
    "entry_volume": 1182017.4249299995
  },
  "MNT": {
    "current_run": 19,
    "status": "post_exit",
    "entry_time": "2026-02-16T09:12:47.664468",
    "exit_time": "2026-02-16T10:11:13.526369",
    "last_bar_collected": 4323,
    "tracking_until": "2026-02-26T10:11:13.526369",
    "entry_volume": 1172929.998516
  },
  "RESOLV": {
    "current_run": 36,
    "status": "post_exit",
    "entry_time": "2026-02-12T19:18:26.077172",
    "exit_time": "2026-02-12T22:32:51.667953",
    "last_bar_collected": 4215,
    "tracking_until": "2026-02-22T22:32:51.667953",
    "entry_volume": 2147282.9249440003
  },
  "ONDO": {
    "current_run": 21,
    "status": "post_exit",
    "entry_time": "2026-02-12T13:18:53.167691",
    "exit_time": "2026-02-12T14:17:06.808319",
    "last_bar_collected": 4258,
    "tracking_until": "2026-02-22T14:17:06.808319",
    "entry_volume": 1099955.1546800002
  },
  "TRUMP": {
    "current_run": 43,
    "status": "post_exit",
    "entry_time": "2026-02-19T03:34:53.440080",
    "exit_time": "2026-02-19T07:58:45.918559",
    "last_bar_collected": 3917,
    "tracking_until": "2026-03-01T07:58:45.918559",
    "entry_volume": 2032816.0624700002
  },
  "AVAX": {
    "current_run": 18,
    "status": "post_exit",
    "entry_time": "2026-02-18T16:09:18.351823",
    "exit_time": "2026-02-18T19:54:01.356238",
    "last_bar_collected": 3885,
    "tracking_until": "2026-02-28T19:54:01.356238",
    "entry_volume": 2900884.307208
  },
  "ADA": {
    "current_run": 29,
    "status": "in_top6",
    "entry_time": "2026-02-19T08:46:10.854526",
    "exit_time": null,
    "last_bar_collected": 3826,
    "tracking_until": null,
    "entry_volume": 1955231.6671600004
  },
  "POL": {
    "current_run": 42,
    "status": "post_exit",
    "entry_time": "2026-02-17T17:34:39.708914",
    "exit_time": "2026-02-17T18:31:12.285937",
    "last_bar_collected": 3781,
    "tracking_until": "2026-02-27T18:31:12.285937",
    "entry_volume": 1295945.4923400003
  },
  "BCH": {
    "current_run": 36,
    "status": "post_exit",
    "entry_time": "2026-02-16T19:49:09.308953",
    "exit_time": "2026-02-16T21:02:23.722992",
    "last_bar_collected": 3692,
    "tracking_until": "2026-02-26T21:02:23.722992",
    "entry_volume": 4872091.073479995
  },
  "MON": {
    "current_run": 30,
    "status": "post_exit",
    "entry_time": "2026-02-19T05:11:45.077072",
    "exit_time": "2026-02-19T07:15:59.218684",
    "last_bar_collected": 3599,
    "tracking_until": "2026-03-01T07:15:59.218684",
    "entry_volume": 4962034.919163002
  },
  "BERA": {
    "current_run": 36,
    "status": "post_exit",
    "entry_time": "2026-02-18T19:54:01.356238",
    "exit_time": "2026-02-18T20:26:47.301323",
    "last_bar_collected": 4184,
    "tracking_until": "2026-02-28T20:26:47.301323",
    "entry_volume": 2113089.081465999
  },
  "MERL": {
    "current_run": 35,
    "status": "post_exit",
    "entry_time": "2026-02-17T10:28:04.914218",
    "exit_time": "2026-02-17T14:36:41.843931",
    "last_bar_collected": 2949,
    "tracking_until": "2026-02-27T14:36:41.843931",
    "entry_volume": 1305263.9985550006
  },
  "kSHIB": {
    "current_run": 12,
    "status": "post_exit",
    "entry_time": "2026-02-16T04:38:46.659089",
    "exit_time": "2026-02-16T05:52:55.629613",
    "last_bar_collected": 4544,
    "tracking_until": "2026-02-26T05:52:55.629613",
    "entry_volume": 1460611.9914539992
  },
  "0G": {
    "current_run": 16,
    "status": "post_exit",
    "entry_time": "2026-02-12T06:14:53.370404",
    "exit_time": "2026-02-12T09:49:28.255954",
    "last_bar_collected": 2539,
    "tracking_until": "2026-02-22T09:49:28.255954",
    "entry_volume": 1538546.5255599997
  },
  "SKY": {
    "current_run": 19,
    "status": "post_exit",
    "entry_time": "2026-02-16T02:34:27.736131",
    "exit_time": "2026-02-16T04:38:46.659089",
    "last_bar_collected": 2514,
    "tracking_until": "2026-02-26T04:38:46.659089",
    "entry_volume": 1174182.368301
  },
  "SKR": {
    "current_run": 32,
    "status": "post_exit",
    "entry_time": "2026-02-13T12:01:03.818632",
    "exit_time": "2026-02-13T13:17:11.130890",
    "last_bar_collected": 1966,
    "tracking_until": "2026-02-23T13:17:11.130890",
    "entry_volume": 1083149.3759200003
  },
  "PYTH": {
    "current_run": 6,
    "status": "post_exit",
    "entry_time": "2026-02-15T16:34:34.107216",
    "exit_time": "2026-02-15T17:29:24.050395",
    "last_bar_collected": 1979,
    "tracking_until": "2026-02-25T17:29:24.050395",
    "entry_volume": 1265862.7212159995
  },
  "UNI": {
    "current_run": 10,
    "status": "post_exit",
    "entry_time": "2026-02-19T03:34:53.440080",
    "exit_time": "2026-02-19T05:11:45.077072",
    "last_bar_collected": 4659,
    "tracking_until": "2026-03-01T05:11:45.077072",
    "entry_volume": 2864639.5095900004
  },
  "HBAR": {
    "current_run": 9,
    "status": "post_exit",
    "entry_time": "2026-02-15T08:52:19.299381",
    "exit_time": "2026-02-15T10:58:03.028928",
    "last_bar_collected": 4132,
    "tracking_until": "2026-02-25T10:58:03.028928",
    "entry_volume": 1419636.1219000001
  },
  "AXS": {
    "current_run": 18,
    "status": "post_exit",
    "entry_time": "2026-02-18T16:09:18.351823",
    "exit_time": "2026-02-18T17:18:24.579763",
    "last_bar_collected": 2758,
    "tracking_until": "2026-02-28T17:18:24.579763",
    "entry_volume": 2146597.9880100004
  },
  "XLM": {
    "current_run": 14,
    "status": "post_exit",
    "entry_time": "2026-02-15T17:52:46.061852",
    "exit_time": "2026-02-15T18:17:05.302512",
    "last_bar_collected": 4702,
    "tracking_until": "2026-02-25T18:17:05.302512",
    "entry_volume": 1682086.8784299993
  },
  "ZK": {
    "current_run": 8,
    "status": "post_exit",
    "entry_time": "2026-02-15T14:00:24.088928",
    "exit_time": "2026-02-15T14:33:24.748418",
    "last_bar_collected": 3267,
    "tracking_until": "2026-02-25T14:33:24.748418",
    "entry_volume": 1394960.9327629998
  },
  "MOODENG": {
    "current_run": 11,
    "status": "post_exit",
    "entry_time": "2026-02-16T19:49:09.308953",
    "exit_time": "2026-02-17T03:32:41.844234",
    "last_bar_collected": 4445,
    "tracking_until": "2026-02-27T03:32:41.844234",
    "entry_volume": 1373505.043129001
  },
  "MOVE": {
    "current_run": 10,
    "status": "post_exit",
    "entry_time": "2026-02-17T11:12:17.077397",
    "exit_time": "2026-02-17T15:31:27.798877",
    "last_bar_collected": 3086,
    "tracking_until": "2026-02-27T15:31:27.798877",
    "entry_volume": 1170288.9492710005
  },
  "MORPHO": {
    "current_run": 11,
    "status": "post_exit",
    "entry_time": "2026-02-18T22:17:38.670001",
    "exit_time": "2026-02-19T03:34:53.440080",
    "last_bar_collected": 3953,
    "tracking_until": "2026-03-01T03:34:53.440080",
    "entry_volume": 3338158.59999
  },
  "WLD": {
    "current_run": 8,
    "status": "post_exit",
    "entry_time": "2026-02-12T10:31:16.145438",
    "exit_time": "2026-02-12T11:24:42.562929",
    "last_bar_collected": 4383,
    "tracking_until": "2026-02-22T11:24:42.562929",
    "entry_volume": 1500013.5335709993
  },
  "ZRO": {
    "current_run": 7,
    "status": "post_exit",
    "entry_time": "2026-02-18T19:54:01.356238",
    "exit_time": "2026-02-18T21:03:42.877681",
    "last_bar_collected": 3909,
    "tracking_until": "2026-02-28T21:03:42.877681",
    "entry_volume": 3652437.6603199975
  },
  "ATOM": {
    "current_run": 12,
    "status": "post_exit",
    "entry_time": "2026-02-19T07:58:45.918559",
    "exit_time": "2026-02-19T08:46:10.854526",
    "last_bar_collected": 3414,
    "tracking_until": "2026-03-01T08:46:10.854526",
    "entry_volume": 2818129.816334
  },
  "OP": {
    "current_run": 4,
    "status": "post_exit",
    "entry_time": "2026-02-13T22:55:11.091554",
    "exit_time": "2026-02-14T00:03:13.926082",
    "last_bar_collected": 4251,
    "tracking_until": "2026-02-24T00:03:13.926082",
    "entry_volume": 3272323.1180879995
  },
  "S": {
    "current_run": 6,
    "status": "post_exit",
    "entry_time": "2026-02-14T22:58:52.820484",
    "exit_time": "2026-02-14T23:46:28.318213",
    "last_bar_collected": 2526,
    "tracking_until": "2026-02-24T23:46:28.318213",
    "entry_volume": 1925317.9701729992
  },
  "INJ": {
    "current_run": 3,
    "status": "post_exit",
    "entry_time": "2026-02-19T03:34:53.440080",
    "exit_time": "2026-02-19T08:46:10.854526",
    "last_bar_collected": 3494,
    "tracking_until": "2026-03-01T08:46:10.854526",
    "entry_volume": 1799582.2750500012
  },
  "OM": {
    "current_run": 7,
    "status": "post_exit",
    "entry_time": "2026-02-16T21:02:23.722992",
    "exit_time": "2026-02-17T00:56:02.134715",
    "last_bar_collected": 1926,
    "tracking_until": "2026-02-27T00:56:02.134715",
    "entry_volume": 1116882.4082279992
  },
  "AERO": {
    "current_run": 4,
    "status": "post_exit",
    "entry_time": "2026-02-16T07:43:02.060413",
    "exit_time": "2026-02-16T11:06:51.110706",
    "last_bar_collected": 3992,
    "tracking_until": "2026-02-26T11:06:51.110706",
    "entry_volume": 1396812.1577400004
  },
  "XPL": {
    "current_run": 11,
    "status": "post_exit",
    "entry_time": "2026-02-18T07:39:41.268635",
    "exit_time": "2026-02-18T13:36:34.884456",
    "last_bar_collected": 3246,
    "tracking_until": "2026-02-28T13:36:34.884456",
    "entry_volume": 3686862.808116001
  },
  "AAVE": {
    "current_run": 6,
    "status": "post_exit",
    "entry_time": "2026-02-18T05:49:34.123674",
    "exit_time": "2026-02-18T08:25:11.037306",
    "last_bar_collected": 3856,
    "tracking_until": "2026-02-28T08:25:11.037306",
    "entry_volume": 5164119.7716000015
  },
  "LINK": {
    "current_run": 7,
    "status": "post_exit",
    "entry_time": "2026-02-18T23:21:32.135817",
    "exit_time": "2026-02-19T05:11:45.077072",
    "last_bar_collected": 3757,
    "tracking_until": "2026-03-01T05:11:45.077072",
    "entry_volume": 3553135.779189999
  },
  "LTC": {
    "current_run": 11,
    "status": "post_exit",
    "entry_time": "2026-02-18T14:29:41.279127",
    "exit_time": "2026-02-19T03:34:53.440080",
    "last_bar_collected": 5204,
    "tracking_until": "2026-03-01T03:34:53.440080",
    "entry_volume": 1297321.1603199998
  },
  "ENA": {
    "current_run": 7,
    "status": "post_exit",
    "entry_time": "2026-02-17T18:31:12.285937",
    "exit_time": "2026-02-17T21:50:35.593638",
    "last_bar_collected": 4150,
    "tracking_until": "2026-02-27T21:50:35.593638",
    "entry_volume": 1497368.4880199998
  },
  "kPEPE": {
    "current_run": 6,
    "status": "post_exit",
    "entry_time": "2026-02-14T15:22:08.973082",
    "exit_time": "2026-02-14T16:38:33.048586",
    "last_bar_collected": 1744,
    "tracking_until": "2026-02-24T16:38:33.048586",
    "entry_volume": 5373470.431523001
  },
  "XMR": {
    "current_run": 11,
    "status": "post_exit",
    "entry_time": "2026-02-18T19:54:01.356238",
    "exit_time": "2026-02-18T21:46:35.173196",
    "last_bar_collected": 851,
    "tracking_until": "2026-02-28T21:46:35.173196",
    "entry_volume": 2294182.97598
  },
  "STBL": {
    "current_run": 3,
    "status": "post_exit",
    "entry_time": "2026-02-13T04:27:25.558158",
    "exit_time": "2026-02-13T05:43:22.621481",
    "last_bar_collected": 1648,
    "tracking_until": "2026-02-23T05:43:22.621481",
    "entry_volume": 1111944.1893280006
  },
  "FTT": {
    "current_run": 1,
    "status": "post_exit",
    "entry_time": "2026-02-11T12:59:50.827947",
    "exit_time": "2026-02-11T16:17:08.501906",
    "last_bar_collected": 1722,
    "tracking_until": "2026-02-21T16:17:08.501906",
    "entry_volume": 1180639.350770001
  },
  "ACE": {
    "current_run": 2,
    "status": "post_exit",
    "entry_time": "2026-02-18T22:55:29.916865",
    "exit_time": "2026-02-18T23:21:32.135817",
    "last_bar_collected": 620,
    "tracking_until": "2026-02-28T23:21:32.135817",
    "entry_volume": 1091795.055038
  },
  "LINEA": {
    "current_run": 3,
    "status": "post_exit",
    "entry_time": "2026-02-13T08:59:47.636351",
    "exit_time": "2026-02-13T09:51:28.417936",
    "last_bar_collected": 1775,
    "tracking_until": "2026-02-23T09:51:28.417936",
    "entry_volume": 1116347.7608
  },
  "TNSR": {
    "current_run": 3,
    "status": "post_exit",
    "entry_time": "2026-02-13T09:51:28.417936",
    "exit_time": "2026-02-13T15:45:01.292711",
    "last_bar_collected": 574,
    "tracking_until": "2026-02-23T15:45:01.292711",
    "entry_volume": 1994470.8040630003
  },
  "ME": {
    "current_run": 1,
    "status": "post_exit",
    "entry_time": "2026-02-12T08:01:07.950882",
    "exit_time": "2026-02-12T14:17:06.808319",
    "last_bar_collected": 1687,
    "tracking_until": "2026-02-22T14:17:06.808319",
    "entry_volume": 1374365.7420050001
  },
  "GRASS": {
    "current_run": 1,
    "status": "post_exit",
    "entry_time": "2026-02-12T08:57:57.166162",
    "exit_time": "2026-02-12T10:31:16.145438",
    "last_bar_collected": 1741,
    "tracking_until": "2026-02-22T10:31:16.145438",
    "entry_volume": 1100851.936501
  },
  "AZTEC": {
    "current_run": 11,
    "status": "in_top6",
    "entry_time": "2026-02-19T05:11:45.077072",
    "exit_time": null,
    "last_bar_collected": 525,
    "tracking_until": null,
    "entry_volume": 1521417.8180439998
  },
  "DYM": {
    "current_run": 1,
    "status": "post_exit",
    "entry_time": "2026-02-12T18:08:24.097917",
    "exit_time": "2026-02-12T23:00:10.342553",
    "last_bar_collected": 529,
    "tracking_until": "2026-02-22T23:00:10.342553",
    "entry_volume": 1418571.9896469994
  },
  "VVV": {
    "current_run": 2,
    "status": "post_exit",
    "entry_time": "2026-02-13T22:17:56.245942",
    "exit_time": "2026-02-13T22:55:11.091554",
    "last_bar_collected": 3591,
    "tracking_until": "2026-02-23T22:55:11.091554",
    "entry_volume": 4929340.724672999
  },
  "DASH": {
    "current_run": 4,
    "status": "post_exit",
    "entry_time": "2026-02-18T04:48:23.603972",
    "exit_time": "2026-02-18T06:44:44.258794",
    "last_bar_collected": 3066,
    "tracking_until": "2026-02-28T06:44:44.258794",
    "entry_volume": 1504020.6118099994
  },
  "COMP": {
    "current_run": 2,
    "status": "post_exit",
    "entry_time": "2026-02-15T05:41:47.892318",
    "exit_time": "2026-02-15T11:42:10.880652",
    "last_bar_collected": 421,
    "tracking_until": "2026-02-25T11:42:10.880652",
    "entry_volume": 1149268.1426700002
  },
  "APEX": {
    "current_run": 4,
    "status": "post_exit",
    "entry_time": "2026-02-15T10:58:03.028928",
    "exit_time": "2026-02-15T11:22:18.124979",
    "last_bar_collected": 2276,
    "tracking_until": "2026-02-25T11:22:18.124979",
    "entry_volume": 1129340.3608000008
  },
  "ENS": {
    "current_run": 3,
    "status": "post_exit",
    "entry_time": "2026-02-15T08:17:22.689413",
    "exit_time": "2026-02-15T08:52:19.299381",
    "last_bar_collected": 365,
    "tracking_until": "2026-02-25T08:52:19.299381",
    "entry_volume": 1091102.3362919996
  },
  "PAXG": {
    "current_run": 1,
    "status": "post_exit",
    "entry_time": "2026-02-15T10:58:03.028928",
    "exit_time": "2026-02-15T22:31:02.727450",
    "last_bar_collected": 2778,
    "tracking_until": "2026-02-25T22:31:02.727450",
    "entry_volume": 3004995.2948999996
  },
  "BNB": {
    "current_run": 4,
    "status": "in_top6",
    "entry_time": "2026-02-19T07:15:59.218684",
    "exit_time": null,
    "last_bar_collected": 3894,
    "tracking_until": null,
    "entry_volume": 3911164.7323800013
  },
  "INIT": {
    "current_run": 3,
    "status": "post_exit",
    "entry_time": "2026-02-19T07:15:59.218684",
    "exit_time": "2026-02-19T07:58:45.918559",
    "last_bar_collected": 1367,
    "tracking_until": "2026-03-01T07:58:45.918559",
    "entry_volume": 2463480.4381580004
  },
  "UMA": {
    "current_run": 3,
    "status": "post_exit",
    "entry_time": "2026-02-17T07:59:34.641999",
    "exit_time": "2026-02-17T11:12:17.077397",
    "last_bar_collected": 150,
    "tracking_until": "2026-02-27T11:12:17.077397",
    "entry_volume": 2145766.6661139997
  },
  "STRK": {
    "current_run": 1,
    "status": "post_exit",
    "entry_time": "2026-02-16T23:23:37.823206",
    "exit_time": "2026-02-16T23:49:26.476345",
    "last_bar_collected": 4217,
    "tracking_until": "2026-02-26T23:49:26.476345",
    "entry_volume": 1395243.9948430005
  },
  "JTO": {
    "current_run": 1,
    "status": "post_exit",
    "entry_time": "2026-02-17T11:54:40.522695",
    "exit_time": "2026-02-17T13:50:36.269635",
    "last_bar_collected": 1506,
    "tracking_until": "2026-02-27T13:50:36.269635",
    "entry_volume": 1987161.6883700013
  },
  "ZORA": {
    "current_run": 2,
    "status": "post_exit",
    "entry_time": "2026-02-18T21:46:35.173196",
    "exit_time": "2026-02-19T03:34:53.440080",
    "last_bar_collected": 3262,
    "tracking_until": "2026-03-01T03:34:53.440080",
    "entry_volume": 3069258.337475001
  },
  "ASTER": {
    "current_run": 1,
    "status": "post_exit",
    "entry_time": "2026-02-18T21:03:42.877681",
    "exit_time": "2026-02-19T03:34:53.440080",
    "last_bar_collected": 0,
    "tracking_until": "2026-03-01T03:34:53.440080",
    "entry_volume": 5066062.13736
  }
}